bayes_pol/__init__.py
bayes_pol/_version.py
bayes_pol/faraday_model.py
bayes_pol-1.1.dist-info/LICENSE
bayes_pol-1.1.dist-info/METADATA
bayes_pol-1.1.dist-info/WHEEL
bayes_pol-1.1.dist-info/top_level.txt
bayes_pol-1.1.dist-info/RECORD
