Metadata-Version: 2.2
Name: bayes_pol
Version: 1.1
Summary: Bayesian Spectral Polarization Models
Home-page: https://github.com/tvwenger/bayes_pol
Author: Trey V. Wenger
Author-email: Trey Wenger <tvwenger@gmail.com>
License: The MIT License (MIT)
Project-URL: Homepage, https://github.com/tvwenger/bayes_pol
Classifier: Programming Language :: Python :: 3
Classifier: License :: OSI Approved :: MIT License
Classifier: Operating System :: OS Independent
Requires-Python: >=3.11,<3.13
License-File: LICENSE
Requires-Dist: bayes_spec>=1.7.2
Dynamic: author
Dynamic: home-page
Dynamic: requires-python
